lona_dropzone/__init__.py
lona_dropzone/components.py
lona_dropzone/static/lona-dropzone/widgets.css
lona_dropzone/static/lona-dropzone/widgets.js
lona_dropzone/static/lona-dropzone/dist/LICENSE
lona_dropzone/static/lona-dropzone/dist/basic.css
lona_dropzone/static/lona-dropzone/dist/basic.css.map
lona_dropzone/static/lona-dropzone/dist/dropzone-min.js
lona_dropzone/static/lona-dropzone/dist/dropzone-min.js.map
lona_dropzone/static/lona-dropzone/dist/dropzone.css
lona_dropzone/static/lona-dropzone/dist/dropzone.css.map
lona_dropzone/static/lona-dropzone/dist/dropzone.js
lona_dropzone/static/lona-dropzone/dist/dropzone.js.map
lona_dropzone/static/lona-dropzone/dist/dropzone.mjs
lona_dropzone/static/lona-dropzone/dist/dropzone.mjs.map
lona_dropzone-0.1.dist-info/LICENSE.txt
lona_dropzone-0.1.dist-info/METADATA
lona_dropzone-0.1.dist-info/WHEEL
lona_dropzone-0.1.dist-info/top_level.txt
lona_dropzone-0.1.dist-info/RECORD
