Metadata-Version: 2.1
Name: lona-dropzone
Version: 0.1
Summary: Dropzone.js bindings for Lona
Author-email: Florian Scherf <mail@florianscherf.de>
License: MIT License
Project-URL: Homepage, https://github.com/lona-web-org/lona-dropzone
Project-URL: Repository, https://github.com/lona-web-org/lona-dropzone
Project-URL: Bug Tracker, https://github.com/lona-web-org/lona-dropzone/issues
Classifier: Development Status :: 4 - Beta
Classifier: License :: OSI Approved :: MIT License
Classifier: Natural Language :: English
Classifier: Programming Language :: Python :: 3 :: Only
Classifier: Topic :: Internet :: WWW/HTTP
Classifier: Topic :: Internet :: WWW/HTTP :: Dynamic Content
Requires-Python: >=3.7
License-File: LICENSE.txt
Requires-Dist: lona >=1.16.1
Provides-Extra: dev
Requires-Dist: build ; extra == 'dev'
Requires-Dist: twine ; extra == 'dev'
Requires-Dist: lona-picocss ; extra == 'dev'
